nudeny/__init__.py
nudeny/nudeny.py
nudeny-0.0.10.dist-info/LICENSE
nudeny-0.0.10.dist-info/METADATA
nudeny-0.0.10.dist-info/WHEEL
nudeny-0.0.10.dist-info/RECORD
