Metadata-Version: 2.1
Name: nudeny
Version: 0.0.10
Summary: Image nudity classification and detection package.
Home-page: https://github.com/Nudeny/Nudeny-python-module
License: MIT
Author: Nudeny
Author-email: thesis.nudeny69@gmail.com
Requires-Python: >=3.7,<4.0
Classifier: License :: OSI Approved :: MIT License
Classifier: Programming Language :: Python :: 3
Classifier: Programming Language :: Python :: 3.7
Classifier: Programming Language :: Python :: 3.8
Classifier: Programming Language :: Python :: 3.9
Classifier: Programming Language :: Python :: 3.10
Classifier: Programming Language :: Python :: 3.11
Requires-Dist: Pillow (==9.4.0)
Requires-Dist: requests (==2.28.2)
Requires-Dist: urllib3 (==1.26.15)
